<?xml version="1.0" encoding="UTF-8" standalone="yes"?>
<orient-server>
    <handlers>
        <handler class="com.orientechnologies.orient.server.handler.distributed.ODistributedServerManager">
            <parameters>
                <parameter name="name" value="default"/>
                <parameter name="security.algorithm" value="Blowfish"/>
                <parameter name="network.multicast.address" value="235.1.1.1"/>
                <parameter name="network.multicast.port" value="2424"/>
                <parameter name="network.multicast.heartbeat" value="10"/>
                <parameter name="server.update.delay" value="5000"/>
                <parameter name="security.key" value="x2g0+jq6P8L7hT2d"/>
            </parameters>
        </handler>
    </handlers>
    <network>
        <protocols>
            <protocol name="binary" implementation="com.orientechnologies.orient.server.network.protocol.binary.ONetworkProtocolBinary"/>
            <protocol name="http" implementation="com.orientechnologies.orient.server.network.protocol.http.ONetworkProtocolHttpDb"/>
            <protocol name="distributed" implementation="com.orientechnologies.orient.server.network.protocol.distributed.ONetworkProtocolDistributed"/>
        </protocols>
        <listeners>
            <listener ip-address="127.0.0.1" port-range="2424-2430" protocol="distributed"/>
            <listener ip-address="127.0.0.1" port-range="2480-2490" protocol="http">
                <commands>
                    <command pattern="POST|*.action GET|*.action" implementation="com.orientechnologies.orient.server.network.protocol.http.command.post.OServerCommandPostAction">
                        <parameters/>
                    </command>
                </commands>
                <parameters/>
            </listener>
        </listeners>
    </network>
    <storages>
        <storage name="temp" path="memory:temp" loaded-at-startup="true"/>
    </storages>
    <users>
        <user name="root" password="FAFF343DD54DA95F05A033A6A59E2F57CDF35058E4D4AF7AE12910B508384C47" resources="*"/>
    </users>
    <properties>
        <entry name="server.cache.staticResources" value="false"/>
        <entry name="log.console.level" value="info"/>
        <entry name="log.file.level" value="fine"/>
    </properties>
</orient-server>
